multi_import/__init__.py
multi_import/cache.py
multi_import/data.py
multi_import/exceptions.py
multi_import/fields.py
multi_import/formats.py
multi_import/helpers/__init__.py
multi_import/helpers/exceptions.py
multi_import/helpers/fields.py
multi_import/helpers/files.py
multi_import/helpers/serializers.py
multi_import/helpers/strings.py
multi_import/helpers/transactions.py
multi_import/importer.py
multi_import/multi_importer.py
django_multi_import-2.0.11.dist-info/METADATA
django_multi_import-2.0.11.dist-info/WHEEL
django_multi_import-2.0.11.dist-info/licenses/LICENSE
django_multi_import-2.0.11.dist-info/RECORD
