Metadata-Version: 2.4
Name: django-multi_import
Version: 2.0.11
Summary: Import/export multi Django resources together atomically.
License: MIT
License-File: LICENSE
Author: Security Compass
Author-email: contact@securitycompass.com
Requires-Python: >=3.12,<3.13
Classifier: Development Status :: 5 - Production/Stable
Classifier: Framework :: Django
Classifier: Intended Audience :: Developers
Classifier: License :: OSI Approved :: MIT License
Classifier: Natural Language :: English
Classifier: Operating System :: OS Independent
Classifier: Programming Language :: Python :: 3
Classifier: Programming Language :: Python :: 3.12
Classifier: Topic :: Software Development :: Libraries :: Python Modules
Requires-Dist: chardet (>=5.2,<6.0)
Requires-Dist: django (>=4.2,<4.3)
Requires-Dist: djangorestframework (>=3.15,<4.0)
Requires-Dist: tablib[html,ods,xls,xlsx,yaml] (>=3.6,<4.0)
Project-URL: Homepage, https://github.com/sdelements/django-multi-import
